mkdocstrings_sourcelink/__init__.py
mkdocstrings_sourcelink/auto_generator.py
mkdocstrings_sourcelink/toolbox.py
mkdocstrings_sourcelink/test/__init__.py
mkdocstrings_sourcelink/test/test_mkdocstrings_sourcelink.py
mkdocstrings_sourcelink-0.3.2.dist-info/LICENSE
mkdocstrings_sourcelink-0.3.2.dist-info/METADATA
mkdocstrings_sourcelink-0.3.2.dist-info/WHEEL
mkdocstrings_sourcelink-0.3.2.dist-info/top_level.txt
mkdocstrings_sourcelink-0.3.2.dist-info/RECORD
