Metadata-Version: 2.1
Name: mkdocstrings-sourcelink
Version: 0.3.2
Summary: Automatic source link generation for mkdocstrings.
Home-page: https://ai2business.github.io/mkdocstrings-sourcelink/
Author: AI2Business
Author-email: ai2business@protonmail.com
License: Apache License 2.0
Download-URL: https://github.com/AI2Business/mkdocstrings-sourcelink
Project-URL: Bug Reports, https://github.com/AI2Business/mkdocstrings-sourcelink/issues
Project-URL: Source, https://github.com/AI2Business/mkdocstrings-sourcelink/tree/main/mkdocstrings_sourcelink
Keywords: markdown,mkdocs,mkdocstrings,docstrings,auto-doc,development
Platform: UNKNOWN
Classifier: Development Status :: 3 - Alpha
Classifier: Natural Language :: English
Classifier: Operating System :: OS Independent
Classifier: Programming Language :: Python :: 3 :: Only
Classifier: Programming Language :: Python :: 3.6
Classifier: Programming Language :: Python :: 3.7
Classifier: Programming Language :: Python :: 3.8
Classifier: Programming Language :: Python :: 3.9
Classifier: Programming Language :: Python :: 3
Classifier: Topic :: Utilities
Classifier: Topic :: Documentation
Classifier: Topic :: Software Development :: Libraries :: Python Modules
Classifier: License :: OSI Approved :: Apache Software License
Requires-Python: >=3.6, <4
Provides-Extra: tests
Requires-Dist: pytest ; extra == 'tests'
Requires-Dist: pytest-cov ; extra == 'tests'
